mgraph_ai_service_semantic_text/__init__.py
mgraph_ai_service_semantic_text/config.py
mgraph_ai_service_semantic_text/fast_api/Semantic_Text__Service__Fast_API.py
mgraph_ai_service_semantic_text/fast_api/__init__.py
mgraph_ai_service_semantic_text/fast_api/lambda_handler.py
mgraph_ai_service_semantic_text/fast_api/routes/Routes__Semantic_Classification.py
mgraph_ai_service_semantic_text/fast_api/routes/Routes__Text_Transformation.py
mgraph_ai_service_semantic_text/fast_api/routes/Routes__Topic_Classification.py
mgraph_ai_service_semantic_text/fast_api/routes/__init__.py
mgraph_ai_service_semantic_text/schemas/Schema__Semantic_Text__Classification.py
mgraph_ai_service_semantic_text/schemas/__init__.py
mgraph_ai_service_semantic_text/schemas/classification/Schema__Classification__Criterion_Filter.py
mgraph_ai_service_semantic_text/schemas/classification/Schema__Classification__Filter_Request.py
mgraph_ai_service_semantic_text/schemas/classification/Schema__Classification__Filter_Response.py
mgraph_ai_service_semantic_text/schemas/classification/Schema__Classification__Multi_Criteria_Filter_Request.py
mgraph_ai_service_semantic_text/schemas/classification/Schema__Classification__Multi_Criteria_Filter_Response.py
mgraph_ai_service_semantic_text/schemas/classification/Schema__Classification__Multi_Criteria_Request.py
mgraph_ai_service_semantic_text/schemas/classification/Schema__Classification__Multi_Criteria_Response.py
mgraph_ai_service_semantic_text/schemas/classification/Schema__Classification__Request.py
mgraph_ai_service_semantic_text/schemas/classification/Schema__Classification__Response.py
mgraph_ai_service_semantic_text/schemas/classification/__init__.py
mgraph_ai_service_semantic_text/schemas/classification/enums/Enum__Classification__Filter_Mode.py
mgraph_ai_service_semantic_text/schemas/classification/enums/Enum__Classification__Logic_Operator.py
mgraph_ai_service_semantic_text/schemas/classification/enums/Enum__Classification__Output_Mode.py
mgraph_ai_service_semantic_text-0.7.0.dist-info/LICENSE
mgraph_ai_service_semantic_text-0.7.0.dist-info/METADATA
mgraph_ai_service_semantic_text-0.7.0.dist-info/WHEEL
mgraph_ai_service_semantic_text-0.7.0.dist-info/RECORD
